mcp_server_freesearch/__init__.py
mcp_server_freesearch/server.py
mcp_server_freesearch-0.1.2.dist-info/METADATA
mcp_server_freesearch-0.1.2.dist-info/WHEEL
mcp_server_freesearch-0.1.2.dist-info/entry_points.txt
mcp_server_freesearch-0.1.2.dist-info/top_level.txt
mcp_server_freesearch-0.1.2.dist-info/RECORD
