Metadata-Version: 2.4
Name: mcp-server-freesearch
Version: 0.1.2
Summary: 基于 SearXNG 的免费搜索 MCP 服务器
Author-email: Jiecheng Yang <yangjiecheng1995@gmail.com>
License-Expression: MIT
Project-URL: Homepage, https://github.com/wzj177/mcp-server-freesearch
Project-URL: Repository, https://github.com/wzj177/mcp-server-freesearch
Project-URL: Issues, https://github.com/wzj177/mcp-server-freesearch/issues
Keywords: mcp,search,searxng,web-search,model-context-protocol
Classifier: Development Status :: 4 - Beta
Classifier: Intended Audience :: Developers
Classifier: Programming Language :: Python :: 3
Classifier: Programming Language :: Python :: 3.10
Classifier: Programming Language :: Python :: 3.11
Classifier: Programming Language :: Python :: 3.12
Classifier: Topic :: Internet :: WWW/HTTP :: Indexing/Search
Classifier: Topic :: Software Development :: Libraries :: Python Modules
Requires-Python: >=3.10
Requires-Dist: httpx>=0.28.1
Requires-Dist: mcp>=1.0.0
Requires-Dist: python-dotenv>=1.0.0
Requires-Dist: beautifulsoup4>=4.12.0
